pyKadabra/__init__.py
pyKadabra/kinesis.py
pykadabra-0.0.2.dist-info/METADATA
pykadabra-0.0.2.dist-info/WHEEL
pykadabra-0.0.2.dist-info/licenses/LICENSE
pykadabra-0.0.2.dist-info/RECORD
