Metadata-Version: 2.1
Name: pyKadabra
Version: 0.0.2
Summary: A wrapper to use pygsheets
Project-URL: Homepage, https://gitlab.com/Meinhard1/magic_sheets
Project-URL: Bug Tracker, https://gitlab.com/Meinhard1/magic_sheets/-/issues
Author-email: Meinhard <meinhardtestca@gmail.com>
License-File: LICENSE
Classifier: License :: OSI Approved :: MIT License
Classifier: Operating System :: OS Independent
Classifier: Programming Language :: Python :: 3
Requires-Python: >=3.7
